tqdm_pandas/__init__.py
tqdm_pandas/_version.py
tqdm_pandas/patcher.py
tqdm_pandas/reader.py
tqdm_pandas-1.7.0.dist-info/licenses/LICENSE
tqdm_pandas-1.7.0.dist-info/METADATA
tqdm_pandas-1.7.0.dist-info/WHEEL
tqdm_pandas-1.7.0.dist-info/top_level.txt
tqdm_pandas-1.7.0.dist-info/RECORD
