Metadata-Version: 2.4
Name: tqdm-pandas
Version: 1.7.0
Summary: Progress bar for pandas file reading operations
Author-email: IshaanJolly <ijolly1997@gmail.com>
License: MIT
Keywords: pandas,progress,tqdm
Requires-Python: >=3.9
License-File: LICENSE
Requires-Dist: pandas>=1.0.0
Requires-Dist: tqdm>=4.0.0
Dynamic: license-file
